sbd.py
ssg.py
eral/__init__.py
eral/alignment_prototyping_functions.py
eral/eral.py
eral/eral_score.py
eral/time_series_alignment.py
eral/time_series_helpers.py
eral-1.1.1.dist-info/METADATA
eral-1.1.1.dist-info/WHEEL
eral-1.1.1.dist-info/top_level.txt
eral-1.1.1.dist-info/RECORD
