Metadata-Version: 2.4
Name: eral
Version: 1.1.1
Summary: Implementation of ERAL algorithm (Stržinar et al., 2024)
Author-email: Žiga Stržinar <ziga.strzinar@ijs.si>
Project-URL: Homepage, https://repo.ijs.si/zstrzinar/eral
Classifier: Programming Language :: Python :: 3
Classifier: Operating System :: OS Independent
Requires-Python: >=3.11
Requires-Dist: dtw-python>=1.5.0
Requires-Dist: numpy>=2.2.0
Requires-Dist: pandas>=2.2.0
Requires-Dist: python-dateutil>=2.8.2
Requires-Dist: scikit-learn>=1.2.1
Requires-Dist: scipy>=1.9.0
Requires-Dist: tslearn>=0.6.3
Requires-Dist: numba>=0.61.0
